<?xml version="1.0" encoding="UTF-8"?>
<itemInfo>
	<itemKey>8630</itemKey>
	<itemName>Dried Tilefish</itemName>
	<itemIcon>00008597.png</itemIcon>
	<itemDesc>A dried tilefish obtained through Drying.\n ※ Drying decreases the value of the fish.</itemDesc>
	<manufacture action="MANUFACTURE_DRY">
		<item>
			<id>8330</id>
			<name>Tilefish</name>
			<icon>00008330.png</icon>
			<desc>An ingredient that can be sold to a Trader or used in Cooking. It can be obtained through Fishing.\n\n- Usage: Fried Fish, Steamed Fish, Fish Soup, etc.</desc>
		</item>
	</manufacture>
</itemInfo>

