<?xml version="1.0" encoding="UTF-8"?>
<itemInfo>
	<itemKey>9518</itemKey>
	<itemName>Design: Calpheon Noble Dress - Witch</itemName>
	<itemIcon>00009501.png</itemIcon>
	<itemDesc>A design required to craft a Capheon Noble costume. This is used in the Witch’s costume. \n- How to Obtain: This can be found in the Calpheon Tailor Amity Shop.</itemDesc>
	<shop>
		<character>
			<name>Merv</name>
		</character>
	</shop>
	<makelist>
		<item>
			<id>14220</id>
			<name>[Witch] Calpheon Noble Dress</name>
			<icon>00014203.png</icon>
			<desc>A dress for Calpheon aristocrats. It&apos;s both fabulous and practical.\n- Item effect: Amity +15% from a conversation\n※ If you use a costume exchange coupon, you&apos;ll get the same dress with an additional effect of moving speed +2. The costume can be equipped in the same slot as the pearl costume.\nIf you exchange it for a costume, you cannot register it to the Marketplace.</desc>
		</item>
	</makelist>
</itemInfo>

