<?xml version="1.0" encoding="UTF-8"?>
<itemInfo>
	<itemKey>5428</itemKey>
	<itemName>Großer Zwergenpilz</itemName>
	<itemIcon>00005428.png</itemIcon>
	<itemDesc>Eine natürliche Ressource, die durch Sammeln erhalten wurde und verwendet werden kann, um andere Materialien durch Alchemie zu verändern.\n– Gewinnung: Kann abhängig von der Sammelstufe des Charakters durch Sammeln mit bloßen Händen oder mithilfe einer Hacke von Zwergenpilzen erhalten werden.</itemDesc>
	<collect>
		<character>
			<name>Zwergenpilz</name>
		</character>
	</collect>
	<node region="Nord-Cienaga – Sammeln"/>
</itemInfo>

