<?xml version="1.0" encoding="UTF-8"?>
<itemInfo>
	<itemKey>24205</itemKey>
	<itemName>Längliche Töpferware</itemName>
	<itemIcon>Pot_Base_56.png</itemIcon>
	<itemDesc>Längliche Töpferware.</itemDesc>
	<house type="16">
		<item>
			<id>4407</id>
			<name>Roher Schlammkristall</name>
			<icon>00004407.png</icon>
			<desc>Eine natürliche Ressource, welche durch Sammeln erhalten wurde und als Material für die Herstellung verwendet wird. Kann durch Alchemie oder Verarbeitung verändert werden. Das Sammeln von Rohem Schlammkristall erfordert eine gewisse Talentstufe.\n– Gewinnung: Kann in der Nähe der Ruinen von Glisch gesammelt werden.</desc>
		</item>
		<item>
			<id>4006</id>
			<name>Grober Stein</name>
			<icon>00004006.png</icon>
			<desc>Eine weiterverarbeitete, natürliche Ressource, welche durch Sammeln erhalten wurde und als Material für die Herstellung verwendet wird. Kann durch Alchemie oder Verarbeitung verändert werden.\n– Gewinnung: Kann mithilfe einer Spitzhacke aus jedem Felsen gesammelt werden.</desc>
		</item>
		<item>
			<id>6656</id>
			<name>Gesäubertes Wasser</name>
			<icon>00006656.png</icon>
			<desc>Wasser, das zur Reinigung gefiltert wurde.\n– Gewinnung: Kann durch Sieben einer Flasche mit Flusswasser gewonnen werden..\n\n※ Wird Gesäubertes Wasser im Garten angewendet, steigt der Wasservorrat stark an.</desc>
		</item>
		<item>
			<id>4901</id>
			<name>Schwarzsteinpulver</name>
			<icon>00004901.png</icon>
			<desc>Ein grundlegender Bestandteil, der in der Herstellung verwendet wird.\n– Gewinnung: Kann bei einer Raffinerie durch Herstellung gewonnen werden.</desc>
		</item>
	</house>
</itemInfo>

