<?xml version="1.0" encoding="UTF-8"?>
<itemInfo>
	<itemKey>55934</itemKey>
	<itemName>Verpackter getrockneter Feilenfisch</itemName>
	<itemIcon>00055934.png</itemIcon>
	<itemDesc>Handelsware, die 10 getrocknete Feilenfische enthält.</itemDesc>
	<house type="17">
		<item>
			<id>8534</id>
			<name>Getrockneter Feilenfisch</name>
			<icon>00008534.png</icon>
			<desc>Ein Getrockneter Feilenfisch, der durch Trocknen gewonnen wurde. Kann an einer Werkbank zu einer Handelsware verarbeitet werden.\n※ Trocknen verringert den Wert des Fisches.</desc>
		</item>
		<item>
			<id>4901</id>
			<name>Schwarzsteinpulver</name>
			<icon>00004901.png</icon>
			<desc>Ein grundlegender Bestandteil, der in der Herstellung verwendet wird.\n– Gewinnung: Kann bei einer Raffinerie durch Herstellung gewonnen werden.</desc>
		</item>
	</house>
</itemInfo>

