<?xml version="1.0" encoding="UTF-8"?>
<itemInfo>
	<itemKey>15001</itemKey>
	<itemName>Magiekristall der Purpurnen Flamme – Präzision</itemName>
	<itemIcon>00045001.png</itemIcon>
	<itemDesc>Ein Schwarzsteinkristall, der in Waffen-Sockel übertragen werden kann.\n– Gegenstandseffekt: Gesamte Genauigkeit +1\n※ Es ist wahrscheinlich, dass dieser Magiekristall bei Eurem Tod zersplittert.\n\n– Gegenstände können durch den Schwarzgeist übertragen werden.</itemDesc>
	<shop>
		<character>
			<name>Corin</name>
		</character>
	</shop>
	<shop>
		<character>
			<name>Greco Gorda</name>
		</character>
	</shop>
	<shop>
		<character>
			<name>Ardan</name>
		</character>
	</shop>
	<shop>
		<character>
			<name>Marsella</name>
		</character>
	</shop>
	<makelist>
		<item>
			<id>4901</id>
			<name>Schwarzsteinpulver</name>
			<icon>00004901.png</icon>
			<desc>Ein grundlegender Bestandteil, der in der Herstellung verwendet wird.\n– Gewinnung: Kann bei einer Raffinerie durch Herstellung gewonnen werden.</desc>
		</item>
	</makelist>
</itemInfo>

