<?xml version="1.0" encoding="UTF-8"?>
<itemInfo>
	<itemKey>702</itemKey>
	<itemName>Élixir de volonté</itemName>
	<itemIcon>00000702.png</itemIcon>
	<itemDesc>Dégâts infligés par les monstres -15 % pendant 5 min.\n- Temps de recharge : 10 min\n L&apos;effet positif s&apos;applique à toute l&apos;équipe lorsque le Souffle d&apos;Aal est utilisé.</itemDesc>
	<alchemy>
		<item>
			<id>5302</id>
			<name>Réactif de poudre pure</name>
			<icon>00005302.png</icon>
			<desc>Un catalyseur utilisé dans divers processus alchimiques.\n- Obtention : s&apos;obtient par artisanat d&apos;alchimie.</desc>
		</item>
		<item>
			<id>5302</id>
			<name>Réactif de poudre pure</name>
			<icon>00005302.png</icon>
			<desc>Un catalyseur utilisé dans divers processus alchimiques.\n- Obtention : s&apos;obtient par artisanat d&apos;alchimie.</desc>
		</item>
		<item>
			<id>6214</id>
			<name>Sang de loup</name>
			<icon>00006214.png</icon>
			<desc>Une ressource naturelle obtenue par récolte capable de modifier d&apos;autres matériaux grâce à l&apos;alchimie.\n- Obtention : s&apos;obtient en utilisant un collecteur de liquides sur un loup mort.</desc>
		</item>
		<item>
			<id>5401</id>
			<name>Herbe de l&apos;aube</name>
			<icon>00005401.png</icon>
			<desc>Un ingrédient naturel obtenu par récolte capable de modifier d&apos;autres matériaux grâce à l&apos;alchimie.\n- Obtention : peut être produit au site du château de Cron et dans la forêt de Balenos. Peut également être récolté directement sur des herbes sauvages à mains nues ou à l&apos;aide d&apos;une houe.\n\n※ Consommer cet objet cru confère un effet positif spécial, mais peut également vous empoisonner !</desc>
		</item>
		<item>
			<id>6656</id>
			<name>Eau purifiée</name>
			<icon>00006656.png</icon>
			<desc>Eau filtrée pour supprimer les impuretés.\n- Obtention : cette eau peut être obtenue en filtrant une bouteille d&apos;eau de rivière.\n\n※ Utiliser de l&apos;eau purifiée sur un jardin augmentera fortement la quantité d&apos;eau du réservoir.</desc>
		</item>
	</alchemy>
</itemInfo>

