<?xml version="1.0" encoding="UTF-8"?>
<itemInfo>
	<itemKey>49001</itemKey>
	<itemName>Permis bateau : barque</itemName>
	<itemIcon>00049001.png</itemIcon>
	<itemDesc>Preuve de propriété d&apos;une [barque] sur les quais.\n- Emplacement d&apos;inventaire : 8, accélération : 100 %, vitesse : 105 %, direction : 100 %, freinage : 100 %\nUtilisable à partir du niveau 8.\n\n※ Utiliser un permis bateau\n 1. Effectuez un clic droit sur le permis bateau et déplacez-le vers le quai sélectionné.\n 2. Adressez-vous au gardien de la traversée en barque et sélectionnez le menu du quai.\n 3. Cliquez sur le menu d&apos;enregistrement des bateaux puis effectuez un clic droit sur le permis bateau.\n 4. Saisissez le nom du bateau puis confirmez pour l&apos;enregistrer.\n 5. Sélectionnez le bateau enregistré puis cliquez sur le menu de recherche.</itemDesc>
	<house type="13">
		<item>
			<id>4669</id>
			<name>Bois équarri utilisable</name>
			<icon>00004669.png</icon>
			<desc>Du bois nécessaire à la construction.\n\n- Obtention : s&apos;obtient en découpant les rondins des arbres de chaque région.</desc>
		</item>
		<item>
			<id>4652</id>
			<name>Contreplaqué de frêne</name>
			<icon>00004652.png</icon>
			<desc>Un ingrédient naturel transformé obtenu par récolte et utilisé en artisanat. Ses propriétés peuvent être modifiées par l&apos;alchimie ou la transformation.\n\n- Obtention : s&apos;obtient en coupant du bois de frêne. Nécessite des connaissances en coupe (débutant).\n\n※ Trouvez Lebyos à Heidel et terminez la requête de travail du frêne pour obtenir les connaissances associées.\n\n※ Pour exécuter la quête liée aux connaissances en transformation pour débutant, vous devez avoir atteint le niveau 14 de récolte et retrouver Ficy à Heidel pour terminer la requête correspondante. Consultez le guide de l&apos;esprit occulte (touche ,) pour plus d&apos;informations.</desc>
		</item>
		<item>
			<id>4055</id>
			<name>Lingot de plomb</name>
			<icon>00004055.png</icon>
			<desc>Un ingrédient naturel transformé obtenu par récolte et utilisé en artisanat. Ses propriétés peuvent être modifiées par l&apos;alchimie ou la transformation.\n\n- Obtention : s&apos;obtient en fondant des fragments de plomb fondu. Nécessite des connaissances en fonte : débutant.\n\n※ Trouvez Flaviano à Heidel et terminez la quête d&apos;eau purifiée pour une expérience pour obtenir les connaissances associées.\n\n※ Pour exécuter la quête liée aux connaissances en transformation pour débutant, vous devez avoir atteint le niveau 4 d&apos;apprenti en récolte et retrouver Ficy à Heidel pour terminer la quête correspondante. Consultez le guide de l&apos;esprit occulte (touche ,) pour plus d&apos;informations.</desc>
		</item>
		<item>
			<id>5001</id>
			<name>Sève de frêne</name>
			<icon>00005001.png</icon>
			<desc>Un ingrédient naturel obtenu par récolte capable de modifier d&apos;autres matériaux grâce à l&apos;alchimie.\n- Obtention : s&apos;obtient en utilisant un collecteur de liquides sur un frêne.</desc>
		</item>
		<item>
			<id>4901</id>
			<name>Poudre de pierre noire</name>
			<icon>00004901.png</icon>
			<desc>Un ingrédient basique de l&apos;artisanat.\n- Obtention : s&apos;obtient par artisanat dans une raffinerie.</desc>
		</item>
	</house>
	<house type="13">
		<item>
			<id>4669</id>
			<name>Bois équarri utilisable</name>
			<icon>00004669.png</icon>
			<desc>Du bois nécessaire à la construction.\n\n- Obtention : s&apos;obtient en découpant les rondins des arbres de chaque région.</desc>
		</item>
		<item>
			<id>4652</id>
			<name>Contreplaqué de frêne</name>
			<icon>00004652.png</icon>
			<desc>Un ingrédient naturel transformé obtenu par récolte et utilisé en artisanat. Ses propriétés peuvent être modifiées par l&apos;alchimie ou la transformation.\n\n- Obtention : s&apos;obtient en coupant du bois de frêne. Nécessite des connaissances en coupe (débutant).\n\n※ Trouvez Lebyos à Heidel et terminez la requête de travail du frêne pour obtenir les connaissances associées.\n\n※ Pour exécuter la quête liée aux connaissances en transformation pour débutant, vous devez avoir atteint le niveau 14 de récolte et retrouver Ficy à Heidel pour terminer la requête correspondante. Consultez le guide de l&apos;esprit occulte (touche ,) pour plus d&apos;informations.</desc>
		</item>
		<item>
			<id>4055</id>
			<name>Lingot de plomb</name>
			<icon>00004055.png</icon>
			<desc>Un ingrédient naturel transformé obtenu par récolte et utilisé en artisanat. Ses propriétés peuvent être modifiées par l&apos;alchimie ou la transformation.\n\n- Obtention : s&apos;obtient en fondant des fragments de plomb fondu. Nécessite des connaissances en fonte : débutant.\n\n※ Trouvez Flaviano à Heidel et terminez la quête d&apos;eau purifiée pour une expérience pour obtenir les connaissances associées.\n\n※ Pour exécuter la quête liée aux connaissances en transformation pour débutant, vous devez avoir atteint le niveau 4 d&apos;apprenti en récolte et retrouver Ficy à Heidel pour terminer la quête correspondante. Consultez le guide de l&apos;esprit occulte (touche ,) pour plus d&apos;informations.</desc>
		</item>
		<item>
			<id>5001</id>
			<name>Sève de frêne</name>
			<icon>00005001.png</icon>
			<desc>Un ingrédient naturel obtenu par récolte capable de modifier d&apos;autres matériaux grâce à l&apos;alchimie.\n- Obtention : s&apos;obtient en utilisant un collecteur de liquides sur un frêne.</desc>
		</item>
		<item>
			<id>4901</id>
			<name>Poudre de pierre noire</name>
			<icon>00004901.png</icon>
			<desc>Un ingrédient basique de l&apos;artisanat.\n- Obtention : s&apos;obtient par artisanat dans une raffinerie.</desc>
		</item>
	</house>
	<house type="13">
		<item>
			<id>4669</id>
			<name>Bois équarri utilisable</name>
			<icon>00004669.png</icon>
			<desc>Du bois nécessaire à la construction.\n\n- Obtention : s&apos;obtient en découpant les rondins des arbres de chaque région.</desc>
		</item>
		<item>
			<id>4652</id>
			<name>Contreplaqué de frêne</name>
			<icon>00004652.png</icon>
			<desc>Un ingrédient naturel transformé obtenu par récolte et utilisé en artisanat. Ses propriétés peuvent être modifiées par l&apos;alchimie ou la transformation.\n\n- Obtention : s&apos;obtient en coupant du bois de frêne. Nécessite des connaissances en coupe (débutant).\n\n※ Trouvez Lebyos à Heidel et terminez la requête de travail du frêne pour obtenir les connaissances associées.\n\n※ Pour exécuter la quête liée aux connaissances en transformation pour débutant, vous devez avoir atteint le niveau 14 de récolte et retrouver Ficy à Heidel pour terminer la requête correspondante. Consultez le guide de l&apos;esprit occulte (touche ,) pour plus d&apos;informations.</desc>
		</item>
		<item>
			<id>4055</id>
			<name>Lingot de plomb</name>
			<icon>00004055.png</icon>
			<desc>Un ingrédient naturel transformé obtenu par récolte et utilisé en artisanat. Ses propriétés peuvent être modifiées par l&apos;alchimie ou la transformation.\n\n- Obtention : s&apos;obtient en fondant des fragments de plomb fondu. Nécessite des connaissances en fonte : débutant.\n\n※ Trouvez Flaviano à Heidel et terminez la quête d&apos;eau purifiée pour une expérience pour obtenir les connaissances associées.\n\n※ Pour exécuter la quête liée aux connaissances en transformation pour débutant, vous devez avoir atteint le niveau 4 d&apos;apprenti en récolte et retrouver Ficy à Heidel pour terminer la quête correspondante. Consultez le guide de l&apos;esprit occulte (touche ,) pour plus d&apos;informations.</desc>
		</item>
		<item>
			<id>5001</id>
			<name>Sève de frêne</name>
			<icon>00005001.png</icon>
			<desc>Un ingrédient naturel obtenu par récolte capable de modifier d&apos;autres matériaux grâce à l&apos;alchimie.\n- Obtention : s&apos;obtient en utilisant un collecteur de liquides sur un frêne.</desc>
		</item>
		<item>
			<id>4901</id>
			<name>Poudre de pierre noire</name>
			<icon>00004901.png</icon>
			<desc>Un ingrédient basique de l&apos;artisanat.\n- Obtention : s&apos;obtient par artisanat dans une raffinerie.</desc>
		</item>
	</house>
</itemInfo>

